cumulusci_stripe/__init__.py
cumulusci_stripe/cumulusci.yml
cumulusci_stripe/example.py
cumulusci_stripe/tasks.py
cumulusci_stripe-0.1.0.dist-info/LICENSE
cumulusci_stripe-0.1.0.dist-info/WHEEL
cumulusci_stripe-0.1.0.dist-info/METADATA
cumulusci_stripe-0.1.0.dist-info/RECORD
