Metadata-Version: 2.1
Name: cumulusci-stripe
Version: 0.1.0
Summary: A plugin for CumulusCI providing tasks for interacting with the Stripe API
Home-page: https://github.com/muselabdx/cumulusci_stripe
License: BSD-3
Author: MuseLab LLC
Author-email: opensource@muselab.com
Requires-Python: >=3.9,<4.0
Classifier: Development Status :: 3 - Alpha
Classifier: Intended Audience :: Developers
Classifier: License :: OSI Approved :: BSD License
Classifier: License :: Other/Proprietary License
Classifier: Operating System :: OS Independent
Classifier: Programming Language :: Python :: 3
Classifier: Programming Language :: Python :: 3.10
Classifier: Programming Language :: Python :: 3.9
Classifier: Topic :: Software Development :: Libraries :: Python Modules
Requires-Dist: cumulusci (>=3.63,<4.0)
Requires-Dist: stripe (>=4.1.0,<5.0.0)
Project-URL: Repository, https://github.com/muselabdx/cumulusci_stripe
